{
"type": "FeatureCollection",
"crs": { "type": "name", "properties": { "name": "urn:ogc:def:crs:OGC:1.3:CRS84" } },
"features": [
{ "type": "Feature", "properties": { "pk": "HUN03975", "launame": "Baksa", "iso3": "HUN", "geo_level": "sau3", "year_ref_geo": 2020, "OLD_SH": null, "WORKAGE_SH": null, "YOUTH_SH": null, "POP_CH": null, "POP_T": null, "pop_density_km2": null, "NETNAT_RATE": null, "BIRTHS_RATE": null, "DEATHS_RATE": null, "NETMIG_RATE": null, "NETMOB_RATE": null, "NETMOBMIG_RATE": null, "SEX_RATIO_TOT": null, "MIGRANT_SH": null, "BUILT_S_NRES": 24.054576786679721, "BUILT_S_RES": 189.54691418652365, "BUILT_S__T": 213.60149097320337, "BUILT_V_NRES": 60.141969848300292, "BUILT_V_RES": 473.91772738591811, "BUILT_V__T": 534.05969723421845, "BUILT_H": 2.5, "BUILT_S_CH_NRES": 39.5158704713049, "BUILT_S_CH_RES": 26.784740388792855, "BUILT_S_CH__T": 28.101146224421292, "DEGURBA_L1": "Rural area", "DEGURBA_L2": "Dispersed rural area", "AIR_TEMP2M": 12.790883091113823, "AIR_TEMP2M_DIFF_1981_2010": 1.3176332606643661, "HOT_DAYS": 2.2, "HOT_DAYS_DIFF_1981_2010": 1.0, "ICING_DAYS": 3.0, "ICING_DAYS_DIFF_1981_2010": -12.066666666666666, "TROPICAL_NIGHTS": 20.4, "TROPICAL_NIGHTS_DIFF_1981_2010": 11.633333333333333, "EXT_PRECIP_DAYS": 2.4, "EXT_PRECIP_DAYS_1981_2010": -0.66666666666666685, "PRECIP_SUM": 677.35194075437244, "PRECIP_SUM_DIFF_1981_2010": -8.0250465270970999, "SOIL_MOIST_L1_CH_1981_2018": -4.3532540950073972, "LST_DAY_SUMMER": 30.576969922306752, "LST_NIGHT_SUMMER": 16.481405391787948, "CDD_T_22C": 183.99432515462394, "HDD_T_15C": 1745.9296092224085, "CDD_T_22C_CH": 75.592352701823444, "HDD_T_15C_CH": -286.11241929372181, "UTCI_GT32": 64.8, "UTCI_GT32_DIFF_1981_2010": 19.833333333333332, "UTCI_GT38": 7.0, "UTCI_GT38_DIFF_1981_2010": 2.6333333333333337, "UTCI_GT46": 0.0, "UTCI_GT46_DIFF_1981_2010": 0.0, "FIRE_TOTAL_AREA_SH": null, "RIVER_FLOOD_RP100_POP_SH": null, "COASTAL_FLOOD_RP100_POP_SH": null, "GREEN_AREA_CAPITA": 5117.8594343882123, "GREEN_AREA_SHARE": 26.657714537621974, "FOREST_CH": 0.0, "SOLAR_POWER_POT": 3.5320578511559995, "WIND_POWER_POT": 196.10791403253549, "OOKLA_FIXED_DOWNLOAD_DEV": -59.694995290091008, "OOKLA_FIXED_UPLOAD_DEV": -3.3250223431269461, "OOKLA_MOBILE_DOWNLOAD_DEV": -64.866904990442279, "OOKLA_MOBILE_UPLOAD_DEV": -46.972230890003054, "MEDIAN_DISP_INC_PC_CURR_PR": null, "GINI": null, "POV_RATE_50": null, "POV_RATE_60": null, "RENT_M2": null, "HOUSING_PRICE_M2": null, "UNEMP_RA_15_64": null, "fuacode": "HU004F", "fuaname_en": "Pécs", "citycode": null, "cityname_en": null, "tl2_id": "HU23", "tl3_id": "HU231", "tl2_name_en": "Southern Transdanubia", "tl3_name_en": "Baranya" }, "geometry": { "type": "Polygon", "coordinates": [ [ [ 18.092759, 45.927058 ], [ 18.107798, 45.928902 ], [ 18.112543, 45.951074 ], [ 18.095223, 45.976856 ], [ 18.094139, 45.976653 ], [ 18.07888, 45.971661 ], [ 18.067208, 45.965735 ], [ 18.069153, 45.933914 ], [ 18.0898, 45.935146 ], [ 18.092759, 45.927058 ] ] ] } }
]
}
