{
"type": "FeatureCollection",
"crs": { "type": "name", "properties": { "name": "urn:ogc:def:crs:OGC:1.3:CRS84" } },
"features": [
{ "type": "Feature", "properties": { "pk": "HUN16391", "launame": "Nagyb치rk치ny", "iso3": "HUN", "geo_level": "sau3", "year_ref_geo": 2020, "OLD_SH": null, "WORKAGE_SH": null, "YOUTH_SH": null, "POP_CH": null, "POP_T": null, "pop_density_km2": null, "NETNAT_RATE": null, "BIRTHS_RATE": null, "DEATHS_RATE": null, "NETMIG_RATE": null, "NETMOB_RATE": null, "NETMOBMIG_RATE": null, "SEX_RATIO_TOT": null, "MIGRANT_SH": null, "BUILT_S_NRES": 0.32792587674460799, "BUILT_S_RES": 97.45185466551527, "BUILT_S__T": 97.779780542259886, "BUILT_V_NRES": 0.82055660560981103, "BUILT_V_RES": 250.30389274341374, "BUILT_V__T": 251.12444934902354, "BUILT_H": 2.5410374232700894, "BUILT_S_CH_NRES": 18.181818181818183, "BUILT_S_CH_RES": 23.877246920798989, "BUILT_S_CH__T": 23.857228779790994, "DEGURBA_L1": "Rural area", "DEGURBA_L2": "Dispersed rural area", "AIR_TEMP2M": 10.625750556225466, "AIR_TEMP2M_DIFF_1981_2010": 1.3714613593215639, "HOT_DAYS": 0.4, "HOT_DAYS_DIFF_1981_2010": 0.26571428571428568, "ICING_DAYS": 12.165714285714287, "ICING_DAYS_DIFF_1981_2010": -15.46952380952381, "TROPICAL_NIGHTS": 3.4285714285714284, "TROPICAL_NIGHTS_DIFF_1981_2010": 2.1523809523809527, "EXT_PRECIP_DAYS": 2.794285714285714, "EXT_PRECIP_DAYS_1981_2010": -0.038095238095238404, "PRECIP_SUM": 713.5559992397441, "PRECIP_SUM_DIFF_1981_2010": 4.8201094457128821, "SOIL_MOIST_L1_CH_1981_2018": -2.1024220124692738, "LST_DAY_SUMMER": 27.943999630386724, "LST_NIGHT_SUMMER": 16.204468337466519, "CDD_T_22C": 72.216021137783329, "HDD_T_15C": 2242.1735393909235, "CDD_T_22C_CH": 39.825943858071369, "HDD_T_15C_CH": -299.34893071165425, "UTCI_GT32": 38.2, "UTCI_GT32_DIFF_1981_2010": 15.666666666666666, "UTCI_GT38": 1.6, "UTCI_GT38_DIFF_1981_2010": 1.2333333333333336, "UTCI_GT46": 0.0, "UTCI_GT46_DIFF_1981_2010": 0.0, "FIRE_TOTAL_AREA_SH": null, "RIVER_FLOOD_RP100_POP_SH": null, "COASTAL_FLOOD_RP100_POP_SH": null, "GREEN_AREA_CAPITA": 12607.314795043685, "GREEN_AREA_SHARE": 97.298351252300549, "FOREST_CH": 0.0, "SOLAR_POWER_POT": 3.3670792722874032, "WIND_POWER_POT": 179.12998850615028, "OOKLA_FIXED_DOWNLOAD_DEV": -9.0017685850569222, "OOKLA_FIXED_UPLOAD_DEV": -4.3647931107872919, "OOKLA_MOBILE_DOWNLOAD_DEV": -35.66004604075043, "OOKLA_MOBILE_UPLOAD_DEV": -26.041535621109915, "MEDIAN_DISP_INC_PC_CURR_PR": null, "GINI": null, "POV_RATE_50": null, "POV_RATE_60": null, "RENT_M2": null, "HOUSING_PRICE_M2": null, "UNEMP_RA_15_64": null, "fuacode": null, "fuaname_en": null, "citycode": null, "cityname_en": null, "tl2_id": "HU31", "tl3_id": "HU313", "tl2_name_en": "Northern Hungary", "tl3_name_en": "N칩gr치d" }, "geometry": { "type": "Polygon", "coordinates": [ [ [ 19.695445, 48.016372 ], [ 19.695899, 48.012977 ], [ 19.690991, 48.009195 ], [ 19.673016, 48.009667 ], [ 19.668576, 47.998085 ], [ 19.669068, 47.997597 ], [ 19.673053, 47.991832 ], [ 19.686834, 47.985121 ], [ 19.700054, 47.985959 ], [ 19.714512, 47.993721 ], [ 19.716942, 48.003468 ], [ 19.71158, 48.011108 ], [ 19.710951, 48.015622 ], [ 19.695445, 48.016372 ] ] ] } }
]
}
