{
"type": "FeatureCollection",
"crs": { "type": "name", "properties": { "name": "urn:ogc:def:crs:OGC:1.3:CRS84" } },
"features": [
{ "type": "Feature", "properties": { "pk": "HUN20950", "launame": "Belsősárd", "iso3": "HUN", "geo_level": "sau3", "year_ref_geo": 2020, "OLD_SH": null, "WORKAGE_SH": null, "YOUTH_SH": null, "POP_CH": null, "POP_T": null, "pop_density_km2": null, "NETNAT_RATE": null, "BIRTHS_RATE": null, "DEATHS_RATE": null, "NETMIG_RATE": null, "NETMOB_RATE": null, "NETMOBMIG_RATE": null, "SEX_RATIO_TOT": null, "MIGRANT_SH": null, "BUILT_S_NRES": 28.125789792453052, "BUILT_S_RES": 239.41480422573932, "BUILT_S__T": 267.54059401819234, "BUILT_V_NRES": 70.341058403431731, "BUILT_V_RES": 598.64866303800454, "BUILT_V__T": 668.98972144143625, "BUILT_H": 2.5, "BUILT_S_CH_NRES": 63.271604938271608, "BUILT_S_CH_RES": 40.569395017793596, "BUILT_S_CH__T": 42.654646481827974, "DEGURBA_L1": "Rural area", "DEGURBA_L2": "Mostly uninhabited area", "AIR_TEMP2M": 12.158631818889422, "AIR_TEMP2M_DIFF_1981_2010": 1.2766160932182884, "HOT_DAYS": 0.2, "HOT_DAYS_DIFF_1981_2010": -0.1, "ICING_DAYS": 3.8, "ICING_DAYS_DIFF_1981_2010": -13.6, "TROPICAL_NIGHTS": 13.2, "TROPICAL_NIGHTS_DIFF_1981_2010": 7.7333333333333343, "EXT_PRECIP_DAYS": 4.4, "EXT_PRECIP_DAYS_1981_2010": -0.43333333333333302, "PRECIP_SUM": 834.16838306518241, "PRECIP_SUM_DIFF_1981_2010": 38.356308549931157, "SOIL_MOIST_L1_CH_1981_2018": 0.045815011947825113, "LST_DAY_SUMMER": 28.860030887279798, "LST_NIGHT_SUMMER": 15.429016355598964, "CDD_T_22C": 118.99357388814406, "HDD_T_15C": 1843.3578168487504, "CDD_T_22C_CH": 49.801716783312017, "HDD_T_15C_CH": -289.66664381239229, "UTCI_GT32": 45.51, "UTCI_GT32_DIFF_1981_2010": 17.506666666666668, "UTCI_GT38": 1.64, "UTCI_GT38_DIFF_1981_2010": 0.71166666666666667, "UTCI_GT46": 0.0, "UTCI_GT46_DIFF_1981_2010": 0.0, "FIRE_TOTAL_AREA_SH": null, "RIVER_FLOOD_RP100_POP_SH": null, "COASTAL_FLOOD_RP100_POP_SH": null, "GREEN_AREA_CAPITA": 40079.574580997454, "GREEN_AREA_SHARE": 37.601075558850752, "FOREST_CH": 0.0, "SOLAR_POWER_POT": 3.4857418853846363, "WIND_POWER_POT": 243.237702172913, "OOKLA_FIXED_DOWNLOAD_DEV": -79.060452618306144, "OOKLA_FIXED_UPLOAD_DEV": -94.4299590931967, "OOKLA_MOBILE_DOWNLOAD_DEV": -99.79145584122476, "OOKLA_MOBILE_UPLOAD_DEV": -66.995431982702286, "MEDIAN_DISP_INC_PC_CURR_PR": null, "GINI": null, "POV_RATE_50": null, "POV_RATE_60": null, "RENT_M2": null, "HOUSING_PRICE_M2": null, "UNEMP_RA_15_64": null, "fuacode": null, "fuaname_en": null, "citycode": null, "cityname_en": null, "tl2_id": "HU22", "tl3_id": "HU223", "tl2_name_en": "Western Transdanubia", "tl3_name_en": "Zala" }, "geometry": { "type": "Polygon", "coordinates": [ [ [ 16.510717, 46.630301 ], [ 16.524835, 46.631568 ], [ 16.529107, 46.635732 ], [ 16.529109, 46.644688 ], [ 16.519935, 46.646754 ], [ 16.510695, 46.654913 ], [ 16.500442, 46.657892 ], [ 16.489341, 46.645028 ], [ 16.471337, 46.645782 ], [ 16.463952, 46.641818 ], [ 16.45982, 46.637019 ], [ 16.466489, 46.633658 ], [ 16.466664, 46.630659 ], [ 16.471063, 46.628733 ], [ 16.475361, 46.632142 ], [ 16.479552, 46.637245 ], [ 16.488269, 46.634273 ], [ 16.488947, 46.629243 ], [ 16.49408, 46.629974 ], [ 16.502591, 46.62406 ], [ 16.510717, 46.630301 ] ] ] } }
]
}
