{
"type": "FeatureCollection",
"crs": { "type": "name", "properties": { "name": "urn:ogc:def:crs:OGC:1.3:CRS84" } },
"features": [
{ "type": "Feature", "properties": { "pk": "HUN27021", "launame": "Kisharsány", "iso3": "HUN", "geo_level": "sau3", "year_ref_geo": 2020, "OLD_SH": null, "WORKAGE_SH": null, "YOUTH_SH": null, "POP_CH": null, "POP_T": null, "pop_density_km2": null, "NETNAT_RATE": null, "BIRTHS_RATE": null, "DEATHS_RATE": null, "NETMIG_RATE": null, "NETMOB_RATE": null, "NETMOBMIG_RATE": null, "SEX_RATIO_TOT": null, "MIGRANT_SH": null, "BUILT_S_NRES": 12.389499884416145, "BUILT_S_RES": 210.38137580604425, "BUILT_S__T": 222.7708756904604, "BUILT_V_NRES": 30.979803212612552, "BUILT_V_RES": 526.0170012816186, "BUILT_V__T": 556.99680449423113, "BUILT_H": 2.5, "BUILT_S_CH_NRES": 19.038386971694454, "BUILT_S_CH_RES": 18.394994435738457, "BUILT_S_CH__T": 18.430594293070158, "DEGURBA_L1": "Rural area", "DEGURBA_L2": "Dispersed rural area", "AIR_TEMP2M": 12.812483370988627, "AIR_TEMP2M_DIFF_1981_2010": 1.3452120100146605, "HOT_DAYS": 2.0, "HOT_DAYS_DIFF_1981_2010": 1.0666666666666664, "ICING_DAYS": 3.4, "ICING_DAYS_DIFF_1981_2010": -12.533333333333335, "TROPICAL_NIGHTS": 22.4, "TROPICAL_NIGHTS_DIFF_1981_2010": 13.066666666666666, "EXT_PRECIP_DAYS": 2.2, "EXT_PRECIP_DAYS_1981_2010": -0.6, "PRECIP_SUM": 672.6716022524422, "PRECIP_SUM_DIFF_1981_2010": -6.9009563224608401, "SOIL_MOIST_L1_CH_1981_2018": -4.3655905037275566, "LST_DAY_SUMMER": 31.159104562079868, "LST_NIGHT_SUMMER": 16.932032812040806, "CDD_T_22C": 183.08517901102849, "HDD_T_15C": 1741.7902391560842, "CDD_T_22C_CH": 78.089028032091392, "HDD_T_15C_CH": -290.22824005974621, "UTCI_GT32": 64.009523809523813, "UTCI_GT32_DIFF_1981_2010": 18.896825396825406, "UTCI_GT38": 7.333333333333333, "UTCI_GT38_DIFF_1981_2010": 3.3730158730158721, "UTCI_GT46": 0.0, "UTCI_GT46_DIFF_1981_2010": 0.0, "FIRE_TOTAL_AREA_SH": null, "RIVER_FLOOD_RP100_POP_SH": null, "COASTAL_FLOOD_RP100_POP_SH": null, "GREEN_AREA_CAPITA": 12945.093187147662, "GREEN_AREA_SHARE": 48.926398210265809, "FOREST_CH": 10.34482758620689, "SOLAR_POWER_POT": 3.5267047802763187, "WIND_POWER_POT": 202.75332913237736, "OOKLA_FIXED_DOWNLOAD_DEV": -9.2292497951424561, "OOKLA_FIXED_UPLOAD_DEV": -62.288944693413455, "OOKLA_MOBILE_DOWNLOAD_DEV": -21.641594217486769, "OOKLA_MOBILE_UPLOAD_DEV": -81.1017400917288, "MEDIAN_DISP_INC_PC_CURR_PR": null, "GINI": null, "POV_RATE_50": null, "POV_RATE_60": null, "RENT_M2": null, "HOUSING_PRICE_M2": null, "UNEMP_RA_15_64": null, "fuacode": null, "fuaname_en": null, "citycode": null, "cityname_en": null, "tl2_id": "HU23", "tl3_id": "HU231", "tl2_name_en": "Southern Transdanubia", "tl3_name_en": "Baranya" }, "geometry": { "type": "Polygon", "coordinates": [ [ [ 18.34411, 45.832352 ], [ 18.348694, 45.818829 ], [ 18.353594, 45.820239 ], [ 18.36129, 45.825314 ], [ 18.363626, 45.837288 ], [ 18.367999, 45.842768 ], [ 18.36458, 45.843944 ], [ 18.36637, 45.848444 ], [ 18.372948, 45.852201 ], [ 18.384295, 45.853431 ], [ 18.391038, 45.877995 ], [ 18.393085, 45.883815 ], [ 18.364443, 45.882329 ], [ 18.358882, 45.879202 ], [ 18.354463, 45.871357 ], [ 18.351411, 45.846531 ], [ 18.34411, 45.832352 ] ] ] } }
]
}
