{
"type": "FeatureCollection",
"crs": { "type": "name", "properties": { "name": "urn:ogc:def:crs:OGC:1.3:CRS84" } },
"features": [
{ "type": "Feature", "properties": { "pk": "HUN26383", "launame": "Gátér", "iso3": "HUN", "geo_level": "sau3", "year_ref_geo": 2020, "OLD_SH": null, "WORKAGE_SH": null, "YOUTH_SH": null, "POP_CH": null, "POP_T": null, "pop_density_km2": null, "NETNAT_RATE": null, "BIRTHS_RATE": null, "DEATHS_RATE": null, "NETMIG_RATE": null, "NETMOB_RATE": null, "NETMOBMIG_RATE": null, "SEX_RATIO_TOT": null, "MIGRANT_SH": null, "BUILT_S_NRES": 0.83712949787076629, "BUILT_S_RES": 174.10850228991472, "BUILT_S__T": 174.94563178778549, "BUILT_V_NRES": 2.0939339960003518, "BUILT_V_RES": 435.34730794044219, "BUILT_V__T": 437.44124193644251, "BUILT_H": 2.5, "BUILT_S_CH_NRES": 11.869436201780417, "BUILT_S_CH_RES": 19.005122367672168, "BUILT_S_CH__T": 18.968810636546898, "DEGURBA_L1": "Rural area", "DEGURBA_L2": "Dispersed rural area", "AIR_TEMP2M": 12.772259724048684, "AIR_TEMP2M_DIFF_1981_2010": 1.3095769297671158, "HOT_DAYS": 3.589285714285714, "HOT_DAYS_DIFF_1981_2010": 1.9154761904761901, "ICING_DAYS": 5.8, "ICING_DAYS_DIFF_1981_2010": -12.791071428571428, "TROPICAL_NIGHTS": 23.05, "TROPICAL_NIGHTS_DIFF_1981_2010": 11.46547619047619, "EXT_PRECIP_DAYS": 2.0, "EXT_PRECIP_DAYS_1981_2010": -0.031547619047618977, "PRECIP_SUM": 640.57184144971336, "PRECIP_SUM_DIFF_1981_2010": 27.334587160254262, "SOIL_MOIST_L1_CH_1981_2018": -1.6608098400525573, "LST_DAY_SUMMER": 34.225447119334454, "LST_NIGHT_SUMMER": 15.797069599319604, "CDD_T_22C": 194.0918634646296, "HDD_T_15C": 1781.926251143952, "CDD_T_22C_CH": 67.588456457305085, "HDD_T_15C_CH": -296.65711734764091, "UTCI_GT32": 57.2, "UTCI_GT32_DIFF_1981_2010": 15.1, "UTCI_GT38": 4.6, "UTCI_GT38_DIFF_1981_2010": 1.0333333333333332, "UTCI_GT46": 0.0, "UTCI_GT46_DIFF_1981_2010": 0.0, "FIRE_TOTAL_AREA_SH": null, "RIVER_FLOOD_RP100_POP_SH": null, "COASTAL_FLOOD_RP100_POP_SH": null, "GREEN_AREA_CAPITA": 11615.145014548661, "GREEN_AREA_SHARE": 34.393958231403786, "FOREST_CH": 0.0, "SOLAR_POWER_POT": 3.5336153099725882, "WIND_POWER_POT": 260.15766056127666, "OOKLA_FIXED_DOWNLOAD_DEV": 67.472945324102753, "OOKLA_FIXED_UPLOAD_DEV": 170.16359476208055, "OOKLA_MOBILE_DOWNLOAD_DEV": -49.373288499141999, "OOKLA_MOBILE_UPLOAD_DEV": 63.149325119890186, "MEDIAN_DISP_INC_PC_CURR_PR": null, "GINI": null, "POV_RATE_50": null, "POV_RATE_60": null, "RENT_M2": null, "HOUSING_PRICE_M2": null, "UNEMP_RA_15_64": null, "fuacode": null, "fuaname_en": null, "citycode": null, "cityname_en": null, "tl2_id": "HU33", "tl3_id": "HU331", "tl2_name_en": "Southern Great Plain", "tl3_name_en": "Bács-Kiskun" }, "geometry": { "type": "Polygon", "coordinates": [ [ [ 19.955299, 46.649321 ], [ 19.966406, 46.640652 ], [ 19.980713, 46.636888 ], [ 19.98527, 46.653581 ], [ 19.992189, 46.660653 ], [ 19.998241, 46.667279 ], [ 20.007908, 46.68008 ], [ 20.010375, 46.696273 ], [ 20.00529, 46.70341 ], [ 19.982627, 46.717957 ], [ 19.927047, 46.669628 ], [ 19.955299, 46.649321 ] ] ] } }
]
}
