{
"type": "FeatureCollection",
"crs": { "type": "name", "properties": { "name": "urn:ogc:def:crs:OGC:1.3:CRS84" } },
"features": [
{ "type": "Feature", "properties": { "pk": "HUN24253", "launame": "Mikóháza", "iso3": "HUN", "geo_level": "sau3", "year_ref_geo": 2020, "OLD_SH": null, "WORKAGE_SH": null, "YOUTH_SH": null, "POP_CH": null, "POP_T": null, "pop_density_km2": null, "NETNAT_RATE": null, "BIRTHS_RATE": null, "DEATHS_RATE": null, "NETMIG_RATE": null, "NETMOB_RATE": null, "NETMOBMIG_RATE": null, "SEX_RATIO_TOT": null, "MIGRANT_SH": null, "BUILT_S_NRES": 10.004700052180366, "BUILT_S_RES": 190.73620683946115, "BUILT_S__T": 200.74090689164152, "BUILT_V_NRES": 25.017578111063838, "BUILT_V_RES": 476.96193336142204, "BUILT_V__T": 501.97951147248591, "BUILT_H": 2.5016782265009843, "BUILT_S_CH_NRES": 81.082981715893112, "BUILT_S_CH_RES": 54.104407332998491, "BUILT_S_CH__T": 55.257226996814715, "DEGURBA_L1": "Rural area", "DEGURBA_L2": "Dispersed rural area", "AIR_TEMP2M": 10.709483322757762, "AIR_TEMP2M_DIFF_1981_2010": 1.4417820539768027, "HOT_DAYS": 0.4, "HOT_DAYS_DIFF_1981_2010": 0.15404040404040406, "ICING_DAYS": 17.981818181818181, "ICING_DAYS_DIFF_1981_2010": -15.073232323232322, "TROPICAL_NIGHTS": 7.172727272727272, "TROPICAL_NIGHTS_DIFF_1981_2010": 5.0378787878787881, "EXT_PRECIP_DAYS": 1.5848484848484847, "EXT_PRECIP_DAYS_1981_2010": -1.7595959595959592, "PRECIP_SUM": 733.27016177200028, "PRECIP_SUM_DIFF_1981_2010": -14.006602503296397, "SOIL_MOIST_L1_CH_1981_2018": -4.2700846740346021, "LST_DAY_SUMMER": 26.735979095044307, "LST_NIGHT_SUMMER": 16.850388833252691, "CDD_T_22C": 91.231427695535416, "HDD_T_15C": 2261.899121674428, "CDD_T_22C_CH": 51.006194032804387, "HDD_T_15C_CH": -314.21005142308104, "UTCI_GT32": 39.6, "UTCI_GT32_DIFF_1981_2010": 17.566666666666666, "UTCI_GT38": 2.4, "UTCI_GT38_DIFF_1981_2010": 1.7333333333333336, "UTCI_GT46": 0.0, "UTCI_GT46_DIFF_1981_2010": 0.0, "FIRE_TOTAL_AREA_SH": null, "RIVER_FLOOD_RP100_POP_SH": null, "COASTAL_FLOOD_RP100_POP_SH": null, "GREEN_AREA_CAPITA": 29130.256717973476, "GREEN_AREA_SHARE": 87.503821236253984, "FOREST_CH": -0.49261083743843997, "SOLAR_POWER_POT": 3.2464220378776361, "WIND_POWER_POT": 180.38349338532359, "OOKLA_FIXED_DOWNLOAD_DEV": -85.509641495036277, "OOKLA_FIXED_UPLOAD_DEV": -83.495743954302043, "OOKLA_MOBILE_DOWNLOAD_DEV": -72.248456839666758, "OOKLA_MOBILE_UPLOAD_DEV": -76.509156640389278, "MEDIAN_DISP_INC_PC_CURR_PR": null, "GINI": null, "POV_RATE_50": null, "POV_RATE_60": null, "RENT_M2": null, "HOUSING_PRICE_M2": null, "UNEMP_RA_15_64": null, "fuacode": null, "fuaname_en": null, "citycode": null, "cityname_en": null, "tl2_id": "HU31", "tl3_id": "HU311", "tl2_name_en": "Northern Hungary", "tl3_name_en": "Borsod-Abaúj-Zemplén" }, "geometry": { "type": "Polygon", "coordinates": [ [ [ 21.55517, 48.42223 ], [ 21.552334, 48.416066 ], [ 21.543788, 48.397455 ], [ 21.549113, 48.39688 ], [ 21.564233, 48.422002 ], [ 21.584361, 48.443285 ], [ 21.606516, 48.449883 ], [ 21.609576, 48.456632 ], [ 21.60609, 48.469207 ], [ 21.588066, 48.475276 ], [ 21.581531, 48.47461 ], [ 21.575532, 48.466378 ], [ 21.564893, 48.462063 ], [ 21.546712, 48.465422 ], [ 21.549599, 48.459373 ], [ 21.548209, 48.442447 ], [ 21.550007, 48.431093 ], [ 21.551345, 48.430692 ], [ 21.556044, 48.425645 ], [ 21.55517, 48.42223 ] ] ] } }
]
}
