{
"type": "FeatureCollection",
"crs": { "type": "name", "properties": { "name": "urn:ogc:def:crs:OGC:1.3:CRS84" } },
"features": [
{ "type": "Feature", "properties": { "pk": "HUN33561", "launame": "Apaj", "iso3": "HUN", "geo_level": "sau3", "year_ref_geo": 2020, "OLD_SH": null, "WORKAGE_SH": null, "YOUTH_SH": null, "POP_CH": null, "POP_T": null, "pop_density_km2": null, "NETNAT_RATE": null, "BIRTHS_RATE": null, "DEATHS_RATE": null, "NETMIG_RATE": null, "NETMOB_RATE": null, "NETMOBMIG_RATE": null, "SEX_RATIO_TOT": null, "MIGRANT_SH": null, "BUILT_S_NRES": 23.335705603692844, "BUILT_S_RES": 163.80431475871777, "BUILT_S__T": 187.14002036241061, "BUILT_V_NRES": 58.348165744543827, "BUILT_V_RES": 409.57426013988669, "BUILT_V__T": 467.92242588443054, "BUILT_H": 2.5, "BUILT_S_CH_NRES": 23.099224173131891, "BUILT_S_CH_RES": 20.666237106053952, "BUILT_S_CH__T": 20.964360587002094, "DEGURBA_L1": "Rural area", "DEGURBA_L2": "Dispersed rural area", "AIR_TEMP2M": 12.534272537682318, "AIR_TEMP2M_DIFF_1981_2010": 1.3700985661514555, "HOT_DAYS": 2.0, "HOT_DAYS_DIFF_1981_2010": 1.3194756554307114, "ICING_DAYS": 4.6134831460674146, "ICING_DAYS_DIFF_1981_2010": -14.108614232209741, "TROPICAL_NIGHTS": 22.964044943820227, "TROPICAL_NIGHTS_DIFF_1981_2010": 13.656803995006243, "EXT_PRECIP_DAYS": 2.1340823970037457, "EXT_PRECIP_DAYS_1981_2010": -0.36791510611735301, "PRECIP_SUM": 603.8473610564937, "PRECIP_SUM_DIFF_1981_2010": -18.606135741015574, "SOIL_MOIST_L1_CH_1981_2018": -4.0918851864722878, "LST_DAY_SUMMER": 32.797875704654835, "LST_NIGHT_SUMMER": 15.642966161777782, "CDD_T_22C": 179.9580474637317, "HDD_T_15C": 1828.3549153629606, "CDD_T_22C_CH": 77.720530062107301, "HDD_T_15C_CH": -293.923446251722, "UTCI_GT32": 50.925773195876289, "UTCI_GT32_DIFF_1981_2010": 17.024054982817866, "UTCI_GT38": 3.1628865979381442, "UTCI_GT38_DIFF_1981_2010": 1.3594501718213059, "UTCI_GT46": 0.0, "UTCI_GT46_DIFF_1981_2010": 0.0, "FIRE_TOTAL_AREA_SH": null, "RIVER_FLOOD_RP100_POP_SH": null, "COASTAL_FLOOD_RP100_POP_SH": null, "GREEN_AREA_CAPITA": 41681.308884935621, "GREEN_AREA_SHARE": 75.460099440702962, "FOREST_CH": 0.0, "SOLAR_POWER_POT": 3.5224342640897488, "WIND_POWER_POT": 293.77822296802384, "OOKLA_FIXED_DOWNLOAD_DEV": -83.492369712593742, "OOKLA_FIXED_UPLOAD_DEV": -84.644855204000109, "OOKLA_MOBILE_DOWNLOAD_DEV": -18.171298355722566, "OOKLA_MOBILE_UPLOAD_DEV": 57.027526701803538, "MEDIAN_DISP_INC_PC_CURR_PR": null, "GINI": null, "POV_RATE_50": null, "POV_RATE_60": null, "RENT_M2": null, "HOUSING_PRICE_M2": null, "UNEMP_RA_15_64": null, "fuacode": "HU001F", "fuaname_en": "Budapest", "citycode": null, "cityname_en": null, "tl2_id": "HU12", "tl3_id": "HU120", "tl2_name_en": "Pest", "tl3_name_en": "Pest" }, "geometry": { "type": "Polygon", "coordinates": [ [ [ 19.074409, 47.124234 ], [ 19.084243, 47.096164 ], [ 19.093275, 47.044846 ], [ 19.100988, 47.064713 ], [ 19.132103, 47.072054 ], [ 19.163958, 47.095618 ], [ 19.167315, 47.112675 ], [ 19.143025, 47.14913 ], [ 19.157477, 47.170504 ], [ 19.124025, 47.195966 ], [ 19.114408, 47.192112 ], [ 19.114537, 47.187159 ], [ 19.100462, 47.177746 ], [ 19.094659, 47.178057 ], [ 19.082249, 47.169244 ], [ 19.075343, 47.167833 ], [ 19.071784, 47.157959 ], [ 19.080731, 47.146305 ], [ 19.083677, 47.13617 ], [ 19.079476, 47.1266 ], [ 19.074409, 47.124234 ] ] ] } }
]
}
