{
"type": "FeatureCollection",
"crs": { "type": "name", "properties": { "name": "urn:ogc:def:crs:OGC:1.3:CRS84" } },
"features": [
{ "type": "Feature", "properties": { "pk": "HUN32072", "launame": "Teklafalu", "iso3": "HUN", "geo_level": "sau3", "year_ref_geo": 2020, "OLD_SH": null, "WORKAGE_SH": null, "YOUTH_SH": null, "POP_CH": null, "POP_T": null, "pop_density_km2": null, "NETNAT_RATE": null, "BIRTHS_RATE": null, "DEATHS_RATE": null, "NETMIG_RATE": null, "NETMOB_RATE": null, "NETMOBMIG_RATE": null, "SEX_RATIO_TOT": null, "MIGRANT_SH": null, "BUILT_S_NRES": 0.14878355889160585, "BUILT_S_RES": 96.236925480062951, "BUILT_S__T": 96.385709038954559, "BUILT_V_NRES": 0.37195889722901465, "BUILT_V_RES": 240.66112609614476, "BUILT_V__T": 241.03308499337376, "BUILT_H": 2.5, "BUILT_S_CH_NRES": 0.0, "BUILT_S_CH_RES": 19.378950768236976, "BUILT_S_CH__T": 19.343250587205819, "DEGURBA_L1": "Rural area", "DEGURBA_L2": "Dispersed rural area", "AIR_TEMP2M": 12.694998481919811, "AIR_TEMP2M_DIFF_1981_2010": 1.2947129573928291, "HOT_DAYS": 2.0, "HOT_DAYS_DIFF_1981_2010": 1.1333333333333333, "ICING_DAYS": 3.2, "ICING_DAYS_DIFF_1981_2010": -11.9, "TROPICAL_NIGHTS": 17.6, "TROPICAL_NIGHTS_DIFF_1981_2010": 9.4333333333333336, "EXT_PRECIP_DAYS": 3.0, "EXT_PRECIP_DAYS_1981_2010": -0.73333333333333339, "PRECIP_SUM": 722.90564585061725, "PRECIP_SUM_DIFF_1981_2010": -4.2801631884868403, "SOIL_MOIST_L1_CH_1981_2018": -2.218342387407779, "LST_DAY_SUMMER": 28.87391421863752, "LST_NIGHT_SUMMER": 15.832181080355946, "CDD_T_22C": 167.65258099874004, "HDD_T_15C": 1747.3974987284309, "CDD_T_22C_CH": 67.396658812629326, "HDD_T_15C_CH": -287.47527415805348, "UTCI_GT32": 61.8, "UTCI_GT32_DIFF_1981_2010": 18.43333333333333, "UTCI_GT38": 5.2, "UTCI_GT38_DIFF_1981_2010": 1.7, "UTCI_GT46": 0.0, "UTCI_GT46_DIFF_1981_2010": 0.0, "FIRE_TOTAL_AREA_SH": null, "RIVER_FLOOD_RP100_POP_SH": null, "COASTAL_FLOOD_RP100_POP_SH": null, "GREEN_AREA_CAPITA": 37713.469646436097, "GREEN_AREA_SHARE": 59.747623457286323, "FOREST_CH": 35.999999999999993, "SOLAR_POWER_POT": 3.5057769552952869, "WIND_POWER_POT": 187.45360756259092, "OOKLA_FIXED_DOWNLOAD_DEV": -70.366370740968975, "OOKLA_FIXED_UPLOAD_DEV": -42.536429461480239, "OOKLA_MOBILE_DOWNLOAD_DEV": -67.109932648371441, "OOKLA_MOBILE_UPLOAD_DEV": -25.198129843451458, "MEDIAN_DISP_INC_PC_CURR_PR": null, "GINI": null, "POV_RATE_50": null, "POV_RATE_60": null, "RENT_M2": null, "HOUSING_PRICE_M2": null, "UNEMP_RA_15_64": null, "fuacode": null, "fuaname_en": null, "citycode": null, "cityname_en": null, "tl2_id": "HU23", "tl3_id": "HU231", "tl2_name_en": "Southern Transdanubia", "tl3_name_en": "Baranya" }, "geometry": { "type": "Polygon", "coordinates": [ [ [ 17.748939, 45.923059 ], [ 17.74998, 45.932181 ], [ 17.764938, 45.941871 ], [ 17.756666, 45.945606 ], [ 17.73797, 45.958737 ], [ 17.725881, 45.956766 ], [ 17.724444, 45.950473 ], [ 17.719513, 45.946624 ], [ 17.703235, 45.946085 ], [ 17.699247, 45.939486 ], [ 17.688271, 45.939704 ], [ 17.67718, 45.935473 ], [ 17.678173, 45.93224 ], [ 17.683672, 45.924848 ], [ 17.698158, 45.923825 ], [ 17.724336, 45.915607 ], [ 17.736772, 45.922619 ], [ 17.747048, 45.923157 ], [ 17.748939, 45.923059 ] ] ] } }
]
}
