{
"type": "FeatureCollection",
"crs": { "type": "name", "properties": { "name": "urn:ogc:def:crs:OGC:1.3:CRS84" } },
"features": [
{ "type": "Feature", "properties": { "pk": "GRC07090504", "launame": "Basiloudiou (Βασιλουδίου)", "iso3": "GRC", "geo_level": "sau3", "year_ref_geo": 2020, "OLD_SH": null, "WORKAGE_SH": null, "YOUTH_SH": null, "POP_CH": null, "POP_T": null, "pop_density_km2": null, "NETNAT_RATE": null, "BIRTHS_RATE": null, "DEATHS_RATE": null, "NETMIG_RATE": null, "NETMOB_RATE": null, "NETMOBMIG_RATE": null, "SEX_RATIO_TOT": null, "MIGRANT_SH": null, "BUILT_S_NRES": 0.11580993801113376, "BUILT_S_RES": 232.14102074331763, "BUILT_S__T": 232.25683068132875, "BUILT_V_NRES": 0.33852135726331406, "BUILT_V_RES": 656.7388568048043, "BUILT_V__T": 657.0773781620677, "BUILT_H": 3.059236989437955, "BUILT_S_CH_NRES": 5.4054054054054053, "BUILT_S_CH_RES": 23.362605628802044, "BUILT_S_CH__T": 23.352127114300359, "DEGURBA_L1": "Rural area", "DEGURBA_L2": "Dispersed rural area", "AIR_TEMP2M": 15.347133141902281, "AIR_TEMP2M_DIFF_1981_2010": 1.0762159504749911, "HOT_DAYS": 1.8025641025641026, "HOT_DAYS_DIFF_1981_2010": 0.32008547008547011, "ICING_DAYS": 0.8, "ICING_DAYS_DIFF_1981_2010": -0.83333333333333326, "TROPICAL_NIGHTS": 72.476923076923072, "TROPICAL_NIGHTS_DIFF_1981_2010": 23.172222222222221, "EXT_PRECIP_DAYS": 7.1589743589743593, "EXT_PRECIP_DAYS_1981_2010": 2.267094017094017, "PRECIP_SUM": 790.69946792898565, "PRECIP_SUM_DIFF_1981_2010": 143.54527112832244, "SOIL_MOIST_L1_CH_1981_2018": 4.5130903733874295, "LST_DAY_SUMMER": 32.739493909970861, "LST_NIGHT_SUMMER": 20.810332318526225, "CDD_T_22C": 319.47608552134159, "HDD_T_15C": 1163.7772288431636, "CDD_T_22C_CH": 78.807571053736268, "HDD_T_15C_CH": -233.54441206983688, "UTCI_GT32": 93.905263157894737, "UTCI_GT32_DIFF_1981_2010": 21.575438596491228, "UTCI_GT38": 12.705263157894738, "UTCI_GT38_DIFF_1981_2010": 4.8368421052631589, "UTCI_GT46": 0.0, "UTCI_GT46_DIFF_1981_2010": 0.0, "FIRE_TOTAL_AREA_SH": null, "RIVER_FLOOD_RP100_POP_SH": 0.0, "COASTAL_FLOOD_RP100_POP_SH": null, "GREEN_AREA_CAPITA": 9482.1042155597479, "GREEN_AREA_SHARE": 27.396845306926785, "FOREST_CH": 0.0, "SOLAR_POWER_POT": 3.9218028170564745, "WIND_POWER_POT": 95.044639685951964, "OOKLA_FIXED_DOWNLOAD_DEV": -52.272788455042203, "OOKLA_FIXED_UPLOAD_DEV": -29.087328331473113, "OOKLA_MOBILE_DOWNLOAD_DEV": -81.305115209374733, "OOKLA_MOBILE_UPLOAD_DEV": -47.976014535334521, "MEDIAN_DISP_INC_PC_CURR_PR": null, "GINI": null, "POV_RATE_50": null, "POV_RATE_60": null, "RENT_M2": null, "HOUSING_PRICE_M2": null, "UNEMP_RA_15_64": null, "fuacode": "EL002F", "fuaname_en": "Thessaloniki", "citycode": null, "cityname_en": null, "tl2_id": "EL52", "tl3_id": "EL522", "tl2_name_en": "Central Macedonia", "tl3_name_en": "Thessalonica" }, "geometry": { "type": "Polygon", "coordinates": [ [ [ 23.164727, 40.623679 ], [ 23.185102, 40.619513 ], [ 23.195093, 40.626252 ], [ 23.204542, 40.667496 ], [ 23.205225, 40.66928 ], [ 23.208224, 40.678876 ], [ 23.185006, 40.682127 ], [ 23.157755, 40.683372 ], [ 23.160363, 40.656923 ], [ 23.155322, 40.643579 ], [ 23.16063, 40.636176 ], [ 23.164727, 40.623679 ] ] ] } }
]
}
