{
"type": "FeatureCollection",
"crs": { "type": "name", "properties": { "name": "urn:ogc:def:crs:OGC:1.3:CRS84" } },
"features": [
{ "type": "Feature", "properties": { "pk": "GRC26020804", "launame": "Akhladeas (Αχλαδέας)", "iso3": "GRC", "geo_level": "sau3", "year_ref_geo": 2020, "OLD_SH": null, "WORKAGE_SH": null, "YOUTH_SH": null, "POP_CH": null, "POP_T": null, "pop_density_km2": null, "NETNAT_RATE": null, "BIRTHS_RATE": null, "DEATHS_RATE": null, "NETMIG_RATE": null, "NETMOB_RATE": null, "NETMOBMIG_RATE": null, "SEX_RATIO_TOT": null, "MIGRANT_SH": null, "BUILT_S_NRES": 0.0, "BUILT_S_RES": 216.37037381142241, "BUILT_S__T": 216.37037381142241, "BUILT_V_NRES": 0.0, "BUILT_V_RES": 541.08126143007178, "BUILT_V__T": 541.08126143007178, "BUILT_H": 2.5, "BUILT_S_CH_NRES": null, "BUILT_S_CH_RES": 14.347698622104954, "BUILT_S_CH__T": 14.347698622104954, "DEGURBA_L1": "Rural area", "DEGURBA_L2": "Dispersed rural area", "AIR_TEMP2M": 14.448978595242613, "AIR_TEMP2M_DIFF_1981_2010": 1.3425411728466556, "HOT_DAYS": 9.8, "HOT_DAYS_DIFF_1981_2010": 4.9, "ICING_DAYS": 2.0, "ICING_DAYS_DIFF_1981_2010": -1.9333333333333331, "TROPICAL_NIGHTS": 35.8, "TROPICAL_NIGHTS_DIFF_1981_2010": 21.93333333333333, "EXT_PRECIP_DAYS": 9.2, "EXT_PRECIP_DAYS_1981_2010": 3.2666666666666666, "PRECIP_SUM": 859.36828810306235, "PRECIP_SUM_DIFF_1981_2010": 118.15720812508508, "SOIL_MOIST_L1_CH_1981_2018": 0.51331829731349199, "LST_DAY_SUMMER": 34.114282444987893, "LST_NIGHT_SUMMER": 18.088292951728192, "CDD_T_22C": 327.33834966023971, "HDD_T_15C": 1411.8908543141645, "CDD_T_22C_CH": 116.97122811635379, "HDD_T_15C_CH": -281.19867307027221, "UTCI_GT32": 47.716129032258067, "UTCI_GT32_DIFF_1981_2010": 15.621505376344089, "UTCI_GT38": 3.3096774193548386, "UTCI_GT38_DIFF_1981_2010": 1.9559139784946236, "UTCI_GT46": 0.0, "UTCI_GT46_DIFF_1981_2010": 0.0, "FIRE_TOTAL_AREA_SH": null, "RIVER_FLOOD_RP100_POP_SH": 0.0, "COASTAL_FLOOD_RP100_POP_SH": null, "GREEN_AREA_CAPITA": 79240.336529679422, "GREEN_AREA_SHARE": 85.844726965446839, "FOREST_CH": 8.5106382978723278, "SOLAR_POWER_POT": 4.0500757731980368, "WIND_POWER_POT": 94.606615174102046, "OOKLA_FIXED_DOWNLOAD_DEV": null, "OOKLA_FIXED_UPLOAD_DEV": null, "OOKLA_MOBILE_DOWNLOAD_DEV": null, "OOKLA_MOBILE_UPLOAD_DEV": null, "MEDIAN_DISP_INC_PC_CURR_PR": null, "GINI": null, "POV_RATE_50": null, "POV_RATE_60": null, "RENT_M2": null, "HOUSING_PRICE_M2": null, "UNEMP_RA_15_64": null, "fuacode": null, "fuaname_en": null, "citycode": null, "cityname_en": null, "tl2_id": "EL61", "tl3_id": "EL611", "tl2_name_en": "Thessaly", "tl3_name_en": "Karditsa, Trikala" }, "geometry": { "type": "Polygon", "coordinates": [ [ [ 21.61965, 39.869315 ], [ 21.605141, 39.873537 ], [ 21.592609, 39.865903 ], [ 21.585197, 39.840587 ], [ 21.591028, 39.829966 ], [ 21.601832, 39.837474 ], [ 21.610148, 39.839669 ], [ 21.611134, 39.828466 ], [ 21.608401, 39.820693 ], [ 21.616882, 39.814947 ], [ 21.624946, 39.811956 ], [ 21.627926, 39.811377 ], [ 21.631879, 39.813769 ], [ 21.629676, 39.818784 ], [ 21.634543, 39.822584 ], [ 21.636392, 39.834516 ], [ 21.620992, 39.853787 ], [ 21.61965, 39.869315 ] ] ] } }
]
}
