{
"type": "FeatureCollection",
"crs": { "type": "name", "properties": { "name": "urn:ogc:def:crs:OGC:1.3:CRS84" } },
"features": [
{ "type": "Feature", "properties": { "pk": "GRC29030203", "launame": "Gumnou (Γυμνού)", "iso3": "GRC", "geo_level": "sau3", "year_ref_geo": 2020, "OLD_SH": null, "WORKAGE_SH": null, "YOUTH_SH": null, "POP_CH": null, "POP_T": null, "pop_density_km2": null, "NETNAT_RATE": null, "BIRTHS_RATE": null, "DEATHS_RATE": null, "NETMIG_RATE": null, "NETMOB_RATE": null, "NETMOBMIG_RATE": null, "SEX_RATIO_TOT": null, "MIGRANT_SH": null, "BUILT_S_NRES": 0.0, "BUILT_S_RES": 135.82469869047515, "BUILT_S__T": 135.82469869047515, "BUILT_V_NRES": 0.0, "BUILT_V_RES": 409.77633721167928, "BUILT_V__T": 409.77633721167928, "BUILT_H": 2.5875459798177083, "BUILT_S_CH_NRES": null, "BUILT_S_CH_RES": 12.189540451464461, "BUILT_S_CH__T": 12.189540451464461, "DEGURBA_L1": "Rural area", "DEGURBA_L2": "Village", "AIR_TEMP2M": 16.151485385728598, "AIR_TEMP2M_DIFF_1981_2010": 0.85295050051173893, "HOT_DAYS": 3.5125, "HOT_DAYS_DIFF_1981_2010": -0.25208333333333338, "ICING_DAYS": 0.1375, "ICING_DAYS_DIFF_1981_2010": -0.4, "TROPICAL_NIGHTS": 62.1875, "TROPICAL_NIGHTS_DIFF_1981_2010": 22.23125, "EXT_PRECIP_DAYS": 5.4375, "EXT_PRECIP_DAYS_1981_2010": 0.8, "PRECIP_SUM": 656.27065389933034, "PRECIP_SUM_DIFF_1981_2010": 90.682592790241486, "SOIL_MOIST_L1_CH_1981_2018": 5.645999506035615, "LST_DAY_SUMMER": 36.352027226473453, "LST_NIGHT_SUMMER": 20.669663541858625, "CDD_T_22C": 293.0540951490425, "HDD_T_15C": 870.98663282711937, "CDD_T_22C_CH": 51.65807811922528, "HDD_T_15C_CH": -194.64172478781757, "UTCI_GT32": 80.822222222222223, "UTCI_GT32_DIFF_1981_2010": 6.8925925925926066, "UTCI_GT38": 13.933333333333332, "UTCI_GT38_DIFF_1981_2010": 0.38148148148148059, "UTCI_GT46": 0.24444444444444446, "UTCI_GT46_DIFF_1981_2010": 0.062962962962962971, "FIRE_TOTAL_AREA_SH": null, "RIVER_FLOOD_RP100_POP_SH": 0.0, "COASTAL_FLOOD_RP100_POP_SH": null, "GREEN_AREA_CAPITA": 21019.580199054166, "GREEN_AREA_SHARE": 97.762375866337308, "FOREST_CH": 17.777777777777771, "SOLAR_POWER_POT": 4.1030811846726518, "WIND_POWER_POT": 287.09633179866597, "OOKLA_FIXED_DOWNLOAD_DEV": -56.409197181225991, "OOKLA_FIXED_UPLOAD_DEV": -68.913867146298145, "OOKLA_MOBILE_DOWNLOAD_DEV": -32.595574935351422, "OOKLA_MOBILE_UPLOAD_DEV": -49.010646279051215, "MEDIAN_DISP_INC_PC_CURR_PR": null, "GINI": null, "POV_RATE_50": null, "POV_RATE_60": null, "RENT_M2": null, "HOUSING_PRICE_M2": null, "UNEMP_RA_15_64": null, "fuacode": null, "fuaname_en": null, "citycode": null, "cityname_en": null, "tl2_id": "EL64", "tl3_id": "EL642", "tl2_name_en": "Central Greece", "tl3_name_en": "Euboea" }, "geometry": { "type": "Polygon", "coordinates": [ [ [ 23.901378, 38.482824 ], [ 23.89691, 38.478007 ], [ 23.866649, 38.477908 ], [ 23.862056, 38.475128 ], [ 23.860139, 38.468337 ], [ 23.850195, 38.461839 ], [ 23.841259, 38.452739 ], [ 23.865891, 38.441085 ], [ 23.877324, 38.423951 ], [ 23.898193, 38.435082 ], [ 23.912299, 38.428062 ], [ 23.921572, 38.428175 ], [ 23.927022, 38.427624 ], [ 23.939497, 38.422736 ], [ 23.937281, 38.429568 ], [ 23.945949, 38.439653 ], [ 23.939057, 38.445305 ], [ 23.93946, 38.450944 ], [ 23.934161, 38.457708 ], [ 23.938877, 38.466649 ], [ 23.938762, 38.480532 ], [ 23.930204, 38.49232 ], [ 23.909313, 38.49016 ], [ 23.901378, 38.482824 ] ] ] } }
]
}
