{
"type": "FeatureCollection",
"crs": { "type": "name", "properties": { "name": "urn:ogc:def:crs:OGC:1.3:CRS84" } },
"features": [
{ "type": "Feature", "properties": { "pk": "GRC23050201", "launame": "Proastiou (Προαστίου)", "iso3": "GRC", "geo_level": "sau3", "year_ref_geo": 2020, "OLD_SH": null, "WORKAGE_SH": null, "YOUTH_SH": null, "POP_CH": null, "POP_T": null, "pop_density_km2": null, "NETNAT_RATE": null, "BIRTHS_RATE": null, "DEATHS_RATE": null, "NETMIG_RATE": null, "NETMOB_RATE": null, "NETMOBMIG_RATE": null, "SEX_RATIO_TOT": null, "MIGRANT_SH": null, "BUILT_S_NRES": 2.848871905594065, "BUILT_S_RES": 162.51554802413884, "BUILT_S__T": 165.36441992973289, "BUILT_V_NRES": 7.123081495966253, "BUILT_V_RES": 418.05136259902741, "BUILT_V__T": 425.1744440949937, "BUILT_H": 2.5261014702822338, "BUILT_S_CH_NRES": 25.636267232237543, "BUILT_S_CH_RES": 23.066522813869959, "BUILT_S_CH__T": 23.109903732976491, "DEGURBA_L1": "Rural area", "DEGURBA_L2": "Village", "AIR_TEMP2M": 15.863158308475727, "AIR_TEMP2M_DIFF_1981_2010": 1.1463704517668312, "HOT_DAYS": 18.632, "HOT_DAYS_DIFF_1981_2010": 5.64, "ICING_DAYS": 0.4, "ICING_DAYS_DIFF_1981_2010": -0.612, "TROPICAL_NIGHTS": 51.8, "TROPICAL_NIGHTS_DIFF_1981_2010": 23.509333333333331, "EXT_PRECIP_DAYS": 9.96, "EXT_PRECIP_DAYS_1981_2010": 3.210666666666667, "PRECIP_SUM": 815.92121333213493, "PRECIP_SUM_DIFF_1981_2010": 135.57764795451402, "SOIL_MOIST_L1_CH_1981_2018": 1.1281391769596638, "LST_DAY_SUMMER": 36.652441270581434, "LST_NIGHT_SUMMER": 19.239090728967682, "CDD_T_22C": 465.05794474792737, "HDD_T_15C": 1144.0914052480025, "CDD_T_22C_CH": 118.36028809526272, "HDD_T_15C_CH": -236.10521019304065, "UTCI_GT32": 114.536, "UTCI_GT32_DIFF_1981_2010": 15.769333333333336, "UTCI_GT38": 33.648, "UTCI_GT38_DIFF_1981_2010": 11.885333333333332, "UTCI_GT46": 0.384, "UTCI_GT46_DIFF_1981_2010": 0.256, "FIRE_TOTAL_AREA_SH": null, "RIVER_FLOOD_RP100_POP_SH": 35.417396444125757, "COASTAL_FLOOD_RP100_POP_SH": null, "GREEN_AREA_CAPITA": 2520.0745090649148, "GREEN_AREA_SHARE": 13.896152587639001, "FOREST_CH": 0.0, "SOLAR_POWER_POT": 4.1050144632970733, "WIND_POWER_POT": 90.704570478291799, "OOKLA_FIXED_DOWNLOAD_DEV": -65.407449459304971, "OOKLA_FIXED_UPLOAD_DEV": -72.38205979563034, "OOKLA_MOBILE_DOWNLOAD_DEV": -50.044040064790053, "OOKLA_MOBILE_UPLOAD_DEV": -8.1764197780426962, "MEDIAN_DISP_INC_PC_CURR_PR": null, "GINI": null, "POV_RATE_50": null, "POV_RATE_60": null, "RENT_M2": null, "HOUSING_PRICE_M2": null, "UNEMP_RA_15_64": null, "fuacode": null, "fuaname_en": null, "citycode": null, "cityname_en": null, "tl2_id": "EL61", "tl3_id": "EL611", "tl2_name_en": "Thessaly", "tl3_name_en": "Karditsa, Trikala" }, "geometry": { "type": "Polygon", "coordinates": [ [ [ 21.878605, 39.475315 ], [ 21.918333, 39.473658 ], [ 21.921306, 39.452849 ], [ 21.929272, 39.449107 ], [ 21.943453, 39.451986 ], [ 21.959869, 39.463065 ], [ 21.964077, 39.483605 ], [ 21.973184, 39.487555 ], [ 21.946738, 39.497803 ], [ 21.936552, 39.495093 ], [ 21.923479, 39.496871 ], [ 21.905239, 39.494021 ], [ 21.896357, 39.505216 ], [ 21.900085, 39.514451 ], [ 21.895799, 39.518269 ], [ 21.884333, 39.518061 ], [ 21.880093, 39.507257 ], [ 21.884445, 39.500318 ], [ 21.873058, 39.491351 ], [ 21.870877, 39.475966 ], [ 21.878605, 39.475315 ] ] ] } }
]
}
