{
"type": "FeatureCollection",
"crs": { "type": "name", "properties": { "name": "urn:ogc:def:crs:OGC:1.3:CRS84" } },
"features": [
{ "type": "Feature", "properties": { "pk": "GRC53010401", "launame": "Pappadou (Παππάδου)", "iso3": "GRC", "geo_level": "sau3", "year_ref_geo": 2020, "OLD_SH": null, "WORKAGE_SH": null, "YOUTH_SH": null, "POP_CH": null, "POP_T": null, "pop_density_km2": null, "NETNAT_RATE": null, "BIRTHS_RATE": null, "DEATHS_RATE": null, "NETMIG_RATE": null, "NETMOB_RATE": null, "NETMOBMIG_RATE": null, "SEX_RATIO_TOT": null, "MIGRANT_SH": null, "BUILT_S_NRES": 3.3026734509560249, "BUILT_S_RES": 113.91647217459007, "BUILT_S__T": 117.21914562554609, "BUILT_V_NRES": 9.1725185820038426, "BUILT_V_RES": 306.88199544579493, "BUILT_V__T": 316.05451402779875, "BUILT_H": 2.5589660441756643, "BUILT_S_CH_NRES": 22.415851038433992, "BUILT_S_CH_RES": 29.78962275919254, "BUILT_S_CH__T": 29.569724065267533, "DEGURBA_L1": "Rural area", "DEGURBA_L2": "Village", "AIR_TEMP2M": 17.296316625470087, "AIR_TEMP2M_DIFF_1981_2010": 0.99908564040433556, "HOT_DAYS": 0.94046387335861026, "HOT_DAYS_DIFF_1981_2010": 0.51191932525996853, "ICING_DAYS": 0.0, "ICING_DAYS_DIFF_1981_2010": -0.17539392462638079, "TROPICAL_NIGHTS": 92.65585179115881, "TROPICAL_NIGHTS_DIFF_1981_2010": 20.853338861160495, "EXT_PRECIP_DAYS": 8.5086017215403196, "EXT_PRECIP_DAYS_1981_2010": -0.54997264350334574, "PRECIP_SUM": 706.84101224631797, "PRECIP_SUM_DIFF_1981_2010": -5.816082021712691, "SOIL_MOIST_L1_CH_1981_2018": -1.3409062496504642, "LST_DAY_SUMMER": 35.134421144096265, "LST_NIGHT_SUMMER": 21.98938273021972, "CDD_T_22C": 370.19969533167773, "HDD_T_15C": 635.58791080240758, "CDD_T_22C_CH": 109.74116391917022, "HDD_T_15C_CH": -164.32652718775819, "UTCI_GT32": 5.4, "UTCI_GT32_DIFF_1981_2010": 3.7666666666666671, "UTCI_GT38": 0.0, "UTCI_GT38_DIFF_1981_2010": 0.0, "UTCI_GT46": 0.0, "UTCI_GT46_DIFF_1981_2010": 0.0, "FIRE_TOTAL_AREA_SH": null, "RIVER_FLOOD_RP100_POP_SH": 0.0, "COASTAL_FLOOD_RP100_POP_SH": null, "GREEN_AREA_CAPITA": 4940.6554525442407, "GREEN_AREA_SHARE": 94.266830751263058, "FOREST_CH": 0.0, "SOLAR_POWER_POT": 4.2933215498994972, "WIND_POWER_POT": 339.79661067059391, "OOKLA_FIXED_DOWNLOAD_DEV": -65.755029100716214, "OOKLA_FIXED_UPLOAD_DEV": -77.156019773262898, "OOKLA_MOBILE_DOWNLOAD_DEV": -71.482456539937999, "OOKLA_MOBILE_UPLOAD_DEV": -52.151861554486089, "MEDIAN_DISP_INC_PC_CURR_PR": null, "GINI": null, "POV_RATE_50": null, "POV_RATE_60": null, "RENT_M2": null, "HOUSING_PRICE_M2": null, "UNEMP_RA_15_64": null, "fuacode": null, "fuaname_en": null, "citycode": null, "cityname_en": null, "tl2_id": "EL41", "tl3_id": "EL411", "tl2_name_en": "North Aegean", "tl3_name_en": "Lesbos, Lemnos" }, "geometry": { "type": "MultiPolygon", "coordinates": [ [ [ [ 26.49183, 39.030719 ], [ 26.490101, 39.025936 ], [ 26.506854, 39.016867 ], [ 26.514116, 39.016777 ], [ 26.523211, 39.026027 ], [ 26.514496, 39.032417 ], [ 26.49183, 39.030719 ] ] ], [ [ [ 26.501877, 39.047805 ], [ 26.493996, 39.052513 ], [ 26.486909, 39.047317 ], [ 26.474148, 39.04762 ], [ 26.449328, 39.039461 ], [ 26.455223, 39.034396 ], [ 26.481773, 39.035552 ], [ 26.489396, 39.032274 ], [ 26.490087, 39.037645 ], [ 26.501877, 39.047805 ] ] ] ] } }
]
}
