{
"type": "FeatureCollection",
"crs": { "type": "name", "properties": { "name": "urn:ogc:def:crs:OGC:1.3:CRS84" } },
"features": [
{ "type": "Feature", "properties": { "pk": "GRC50010201", "launame": "Magoulas (Μαγούλας)", "iso3": "GRC", "geo_level": "sau3", "year_ref_geo": 2020, "OLD_SH": null, "WORKAGE_SH": null, "YOUTH_SH": null, "POP_CH": null, "POP_T": null, "pop_density_km2": null, "NETNAT_RATE": null, "BIRTHS_RATE": null, "DEATHS_RATE": null, "NETMIG_RATE": null, "NETMOB_RATE": null, "NETMOBMIG_RATE": null, "SEX_RATIO_TOT": null, "MIGRANT_SH": null, "BUILT_S_NRES": 188.22419731285513, "BUILT_S_RES": 167.49795400155642, "BUILT_S__T": 355.72215131441158, "BUILT_V_NRES": 1434.101666429498, "BUILT_V_RES": 1220.1291629589766, "BUILT_V__T": 2654.2308293884744, "BUILT_H": 5.9170815657632074, "BUILT_S_CH_NRES": 38.33857596093528, "BUILT_S_CH_RES": 28.970768086340371, "BUILT_S_CH__T": 33.763656864895651, "DEGURBA_L1": "Town and semi-dense area", "DEGURBA_L2": "Dense town", "AIR_TEMP2M": 17.482553968828483, "AIR_TEMP2M_DIFF_1981_2010": 0.84664807497010131, "HOT_DAYS": 13.519298245614033, "HOT_DAYS_DIFF_1981_2010": 3.0327485380116972, "ICING_DAYS": 0.0, "ICING_DAYS_DIFF_1981_2010": -0.11695906432748537, "TROPICAL_NIGHTS": 80.508771929824562, "TROPICAL_NIGHTS_DIFF_1981_2010": 19.952046783625736, "EXT_PRECIP_DAYS": 3.284210526315789, "EXT_PRECIP_DAYS_1981_2010": 0.61637426900584757, "PRECIP_SUM": 462.67987087541769, "PRECIP_SUM_DIFF_1981_2010": 75.814425215675072, "SOIL_MOIST_L1_CH_1981_2018": 5.9936474420935637, "LST_DAY_SUMMER": 40.225409655083659, "LST_NIGHT_SUMMER": 22.585875200913939, "CDD_T_22C": 509.41150449920394, "HDD_T_15C": 721.88085456803196, "CDD_T_22C_CH": 87.525626149019843, "HDD_T_15C_CH": -165.05082379153328, "UTCI_GT32": 83.777777777777786, "UTCI_GT32_DIFF_1981_2010": 7.718518518518513, "UTCI_GT38": 15.111111111111109, "UTCI_GT38_DIFF_1981_2010": 4.0037037037037031, "UTCI_GT46": 0.066666666666666666, "UTCI_GT46_DIFF_1981_2010": 0.011111111111111099, "FIRE_TOTAL_AREA_SH": null, "RIVER_FLOOD_RP100_POP_SH": 0.0, "COASTAL_FLOOD_RP100_POP_SH": null, "GREEN_AREA_CAPITA": 2345.1997268295427, "GREEN_AREA_SHARE": 71.295533614277943, "FOREST_CH": 4.5454545454545459, "SOLAR_POWER_POT": 4.2568995902260793, "WIND_POWER_POT": 444.2872212209424, "OOKLA_FIXED_DOWNLOAD_DEV": 11.236727122933598, "OOKLA_FIXED_UPLOAD_DEV": 45.927096542038399, "OOKLA_MOBILE_DOWNLOAD_DEV": -32.699022316989897, "OOKLA_MOBILE_UPLOAD_DEV": -27.604161889828806, "MEDIAN_DISP_INC_PC_CURR_PR": null, "GINI": null, "POV_RATE_50": null, "POV_RATE_60": null, "RENT_M2": null, "HOUSING_PRICE_M2": null, "UNEMP_RA_15_64": null, "fuacode": null, "fuaname_en": null, "citycode": null, "cityname_en": null, "tl2_id": "EL30", "tl3_id": "EL306", "tl2_name_en": "Attica", "tl3_name_en": "Western Attica" }, "geometry": { "type": "Polygon", "coordinates": [ [ [ 23.547646, 38.100497 ], [ 23.545476, 38.116681 ], [ 23.534464, 38.122636 ], [ 23.531663, 38.127719 ], [ 23.502847, 38.130593 ], [ 23.504218, 38.125037 ], [ 23.51945, 38.10833 ], [ 23.518902, 38.098907 ], [ 23.511983, 38.082099 ], [ 23.519089, 38.068587 ], [ 23.528027, 38.067469 ], [ 23.540161, 38.07349 ], [ 23.540691, 38.090274 ], [ 23.547646, 38.100497 ] ] ] } }
]
}
