{
"type": "FeatureCollection",
"crs": { "type": "name", "properties": { "name": "urn:ogc:def:crs:OGC:1.3:CRS84" } },
"features": [
{ "type": "Feature", "properties": { "pk": "CAN4811008", "launame": "Ma-Me-O Beach", "iso3": "CAN", "geo_level": "sau3", "year_ref_geo": 2020, "OLD_SH": 59.663865546218489, "WORKAGE_SH": 40.336134453781511, "YOUTH_SH": 0.0, "POP_CH": null, "POP_T": 119.0, "pop_density_km2": 212.26594945416514, "NETNAT_RATE": null, "BIRTHS_RATE": null, "DEATHS_RATE": null, "NETMIG_RATE": null, "NETMOB_RATE": null, "NETMOBMIG_RATE": null, "SEX_RATIO_TOT": 108.7719298245614, "MIGRANT_SH": 9.0909090909090917, "BUILT_S_NRES": 0.0, "BUILT_S_RES": 408.78381100054264, "BUILT_S__T": 408.78381100054264, "BUILT_V_NRES": null, "BUILT_V_RES": null, "BUILT_V__T": 1022.1139575947403, "BUILT_H": 2.5, "BUILT_S_CH_NRES": null, "BUILT_S_CH_RES": 19.716580879977602, "BUILT_S_CH__T": 19.716580879977602, "DEGURBA_L1": "Rural area", "DEGURBA_L2": "Dispersed rural area", "AIR_TEMP2M": 3.1284260910820763, "AIR_TEMP2M_DIFF_1981_2010": -0.35118975518859452, "HOT_DAYS": 0.0, "HOT_DAYS_DIFF_1981_2010": 0.0, "ICING_DAYS": 87.8, "ICING_DAYS_DIFF_1981_2010": 8.4, "TROPICAL_NIGHTS": 0.6, "TROPICAL_NIGHTS_DIFF_1981_2010": 0.53333333333333321, "EXT_PRECIP_DAYS": 3.8, "EXT_PRECIP_DAYS_1981_2010": 0.7, "PRECIP_SUM": 621.2312113079613, "PRECIP_SUM_DIFF_1981_2010": 44.516595860610849, "SOIL_MOIST_L1_CH_1981_2018": 0.15089490324706745, "LST_DAY_SUMMER": 18.842713760209062, "LST_NIGHT_SUMMER": 15.105776133652364, "CDD_T_22C": 7.040429255167771, "HDD_T_15C": 4485.3917878977318, "CDD_T_22C_CH": 5.0255417082045613, "HDD_T_15C_CH": 159.40633241017713, "UTCI_GT32": 8.8, "UTCI_GT32_DIFF_1981_2010": 4.5333333333333341, "UTCI_GT38": 0.0, "UTCI_GT38_DIFF_1981_2010": 0.0, "UTCI_GT46": 0.0, "UTCI_GT46_DIFF_1981_2010": 0.0, "FIRE_TOTAL_AREA_SH": null, "RIVER_FLOOD_RP100_POP_SH": 0.0, "COASTAL_FLOOD_RP100_POP_SH": null, "GREEN_AREA_CAPITA": 3026.1887357917444, "GREEN_AREA_SHARE": 73.277771030120874, "FOREST_CH": 0.0, "SOLAR_POWER_POT": 4.1033760917588298, "WIND_POWER_POT": 471.50117928084046, "OOKLA_FIXED_DOWNLOAD_DEV": -76.960205578305931, "OOKLA_FIXED_UPLOAD_DEV": -88.781617234016394, "OOKLA_MOBILE_DOWNLOAD_DEV": -86.839924339962067, "OOKLA_MOBILE_UPLOAD_DEV": -92.445867229642545, "MEDIAN_DISP_INC_PC_CURR_PR": null, "GINI": null, "POV_RATE_50": null, "POV_RATE_60": null, "RENT_M2": null, "HOUSING_PRICE_M2": null, "UNEMP_RA_15_64": null, "fuacode": null, "fuaname_en": null, "citycode": null, "cityname_en": null, "tl2_id": "CA48", "tl3_id": "CA4811", "tl2_name_en": "Alberta", "tl3_name_en": "Division No. 11" }, "geometry": { "type": "Polygon", "coordinates": [ [ [ -113.976110997766199, 52.967382386563784 ], [ -113.97440820476163, 52.966102285525686 ], [ -113.947163679931876, 52.980852600541738 ], [ -113.955805611460036, 52.982228149469307 ], [ -113.962512116903724, 52.975428963547067 ], [ -113.976110997766199, 52.967382386563784 ] ] ] } }
]
}
