{
"type": "FeatureCollection",
"crs": { "type": "name", "properties": { "name": "urn:ogc:def:crs:OGC:1.3:CRS84" } },
"features": [
{ "type": "Feature", "properties": { "pk": "CAN4710840", "launame": "Muskowekwan 85-29", "iso3": "CAN", "geo_level": "sau3", "year_ref_geo": 2020, "OLD_SH": 60.0, "WORKAGE_SH": 40.0, "YOUTH_SH": 0.0, "POP_CH": null, "POP_T": 5.0, "pop_density_km2": 2.3952107935436318, "NETNAT_RATE": null, "BIRTHS_RATE": null, "DEATHS_RATE": null, "NETMIG_RATE": null, "NETMOB_RATE": null, "NETMOBMIG_RATE": null, "SEX_RATIO_TOT": 400.0, "MIGRANT_SH": null, "BUILT_S_NRES": 0.0, "BUILT_S_RES": 109.2085489836825, "BUILT_S__T": 109.2085489836825, "BUILT_V_NRES": null, "BUILT_V_RES": null, "BUILT_V__T": 273.17179745780635, "BUILT_H": 2.5, "BUILT_S_CH_NRES": null, "BUILT_S_CH_RES": 5.2173913043478262, "BUILT_S_CH__T": 5.2173913043478262, "DEGURBA_L1": "Rural area", "DEGURBA_L2": "Mostly uninhabited area", "AIR_TEMP2M": 2.1638660017686449, "AIR_TEMP2M_DIFF_1981_2010": -0.0066553155250859142, "HOT_DAYS": 0.0, "HOT_DAYS_DIFF_1981_2010": -0.13333333333333333, "ICING_DAYS": 115.2, "ICING_DAYS_DIFF_1981_2010": 2.9666666666666659, "TROPICAL_NIGHTS": 1.0, "TROPICAL_NIGHTS_DIFF_1981_2010": -0.33333333333333326, "EXT_PRECIP_DAYS": 2.4, "EXT_PRECIP_DAYS_1981_2010": -0.3, "PRECIP_SUM": 496.40709120364829, "PRECIP_SUM_DIFF_1981_2010": -34.668995280771938, "SOIL_MOIST_L1_CH_1981_2018": -7.6990299796048101, "LST_DAY_SUMMER": 28.406467343888231, "LST_NIGHT_SUMMER": 10.62352141584055, "CDD_T_22C": 17.52655403137236, "HDD_T_15C": 4948.7043524424098, "CDD_T_22C_CH": 2.7772458267212929, "HDD_T_15C_CH": 50.048525021870773, "UTCI_GT32": 9.4, "UTCI_GT32_DIFF_1981_2010": 3.7666666666666671, "UTCI_GT38": 0.2, "UTCI_GT38_DIFF_1981_2010": 0.1, "UTCI_GT46": 0.0, "UTCI_GT46_DIFF_1981_2010": 0.0, "FIRE_TOTAL_AREA_SH": null, "RIVER_FLOOD_RP100_POP_SH": 0.0, "COASTAL_FLOOD_RP100_POP_SH": null, "GREEN_AREA_CAPITA": 68875.969682248295, "GREEN_AREA_SHARE": 54.753147286363507, "FOREST_CH": 0.0, "SOLAR_POWER_POT": 4.210998944066386, "WIND_POWER_POT": 415.94306998262653, "OOKLA_FIXED_DOWNLOAD_DEV": null, "OOKLA_FIXED_UPLOAD_DEV": null, "OOKLA_MOBILE_DOWNLOAD_DEV": null, "OOKLA_MOBILE_UPLOAD_DEV": null, "MEDIAN_DISP_INC_PC_CURR_PR": null, "GINI": null, "POV_RATE_50": null, "POV_RATE_60": null, "RENT_M2": null, "HOUSING_PRICE_M2": null, "UNEMP_RA_15_64": null, "fuacode": null, "fuaname_en": null, "citycode": null, "cityname_en": null, "tl2_id": "CA47", "tl3_id": "CA4710", "tl2_name_en": "Saskatchewan", "tl3_name_en": "Division No. 10" }, "geometry": { "type": "MultiPolygon", "coordinates": [ [ [ [ -103.984353720076882, 51.250014304334094 ], [ -103.98435381644191, 51.255425378308274 ], [ -103.995574973167848, 51.255430516531909 ], [ -103.99584545664591, 51.247855226278134 ], [ -103.98445888673038, 51.247770302527421 ], [ -103.984353720076882, 51.250014304334094 ] ] ], [ [ [ -103.975968267245534, 51.278095118245211 ], [ -103.987724325838329, 51.278216432975874 ], [ -103.987539611041768, 51.270365261575776 ], [ -103.995701916067532, 51.270367293540154 ], [ -103.99621717336008, 51.262344638988608 ], [ -103.984718803651887, 51.262714708977633 ], [ -103.984378217003396, 51.270364308734372 ], [ -103.975770213802605, 51.270354990809722 ], [ -103.975968267245534, 51.278095118245211 ] ] ] ] } }
]
}
